spinbar/__init__.py
spinbar-0.3.3.dist-info/METADATA
spinbar-0.3.3.dist-info/WHEEL
spinbar-0.3.3.dist-info/top_level.txt
spinbar-0.3.3.dist-info/RECORD
